nufftax/__init__.py
nufftax/core/__init__.py
nufftax/core/deconvolve.py
nufftax/core/kernel.py
nufftax/core/spread.py
nufftax/transforms/__init__.py
nufftax/transforms/autodiff.py
nufftax/transforms/nufft1.py
nufftax/transforms/nufft2.py
nufftax/transforms/nufft3.py
nufftax/utils/__init__.py
nufftax/utils/grid.py
nufftax-0.3.0.dist-info/licenses/LICENSE
nufftax-0.3.0.dist-info/METADATA
nufftax-0.3.0.dist-info/WHEEL
nufftax-0.3.0.dist-info/top_level.txt
nufftax-0.3.0.dist-info/RECORD
