Metadata-Version: 2.4
Name: nufftax
Version: 0.3.0
Summary: Pure JAX implementation of Non-Uniform FFT
Author: Jacopo Iollo
Author-email: Geoffroy Oudoumanessah <geoffroy.oudoumanesah@gmail.com>
License-Expression: MIT
Project-URL: Homepage, https://github.com/geoffroyO/nufftax
Project-URL: Documentation, https://nufftax.readthedocs.io
Project-URL: Repository, https://github.com/geoffroyO/nufftax
Keywords: jax,fft,nufft,non-uniform,fourier-transform,autodiff
Classifier: Development Status :: 3 - Alpha
Classifier: Intended Audience :: Science/Research
Classifier: Programming Language :: Python :: 3
Classifier: Programming Language :: Python :: 3.12
Classifier: Programming Language :: Python :: 3.13
Classifier: Topic :: Scientific/Engineering :: Mathematics
Requires-Python: >=3.12
License-File: LICENSE
Requires-Dist: jax>=0.4.0
Requires-Dist: jaxlib>=0.4.0
Provides-Extra: dev
Requires-Dist: pytest>=7.0; extra == "dev"
Requires-Dist: pytest-cov; extra == "dev"
Requires-Dist: finufft>=2.0; extra == "dev"
Requires-Dist: numpy>=1.20; extra == "dev"
Requires-Dist: ruff>=0.4.0; extra == "dev"
Requires-Dist: pre-commit>=3.0; extra == "dev"
Provides-Extra: docs
Requires-Dist: sphinx>=7.0; extra == "docs"
Requires-Dist: sphinx-book-theme>=1.0; extra == "docs"
Requires-Dist: sphinx-autobuild>=2024.0; extra == "docs"
Requires-Dist: myst-nb>=1.0; extra == "docs"
Requires-Dist: sphinx-autodoc-typehints>=1.24; extra == "docs"
Requires-Dist: sphinx-design>=0.5; extra == "docs"
Requires-Dist: sphinx-copybutton>=0.5; extra == "docs"
Requires-Dist: sphinx-togglebutton>=0.3; extra == "docs"
Requires-Dist: matplotlib>=3.5; extra == "docs"
Requires-Dist: scipy>=1.9; extra == "docs"
Dynamic: license-file
